lahc/__init__.py
lahc/_lahc.py
lahc/tests.py
lahc-1.0.5.dist-info/LICENSE
lahc-1.0.5.dist-info/METADATA
lahc-1.0.5.dist-info/WHEEL
lahc-1.0.5.dist-info/top_level.txt
lahc-1.0.5.dist-info/RECORD
