Metadata-Version: 2.1
Name: lahc
Version: 1.0.5
Summary: Late Acceptance Hill Climbing in Python
Home-page: https://github.com/gunnstein/lahc
Author: Gunnstein T. Frøseth
Author-email: gunnstein@mailbox.org
License: ISC
Platform: UNKNOWN
Classifier: License :: OSI Approved :: ISC License (ISCL)
Classifier: Operating System :: OS Independent
Classifier: Programming Language :: Python
Classifier: Topic :: Scientific/Engineering
